pulumi_str
