Metadata-Version: 2.1
Name: pulumi-str
Version: 0.0.7
Summary: Basic string manipulation funcions
Home-page: https://github.com/pulumi/pulumi-str
License: UNKNOWN
Project-URL: Repository, https://github.com/pulumi/pulumi-str
Platform: UNKNOWN
